dotlib/__init__.py
dotlib/core.py
dotlib/meta_reflex.py
dotlib/router.py
dotlib/settings.py
dotlib/utils.py
dotlib/utils.py.log
dotlib-0.0.8.dist-info/AUTHORS
dotlib-0.0.8.dist-info/METADATA
dotlib-0.0.8.dist-info/WHEEL
dotlib-0.0.8.dist-info/entry_points.txt
dotlib-0.0.8.dist-info/pbr.json
dotlib-0.0.8.dist-info/top_level.txt
dotlib-0.0.8.dist-info/RECORD
