Metadata-Version: 2.1
Name: dotlib
Version: 0.0.8
Summary: awsome project created by pycman.
Home-page: http://example.com
Author: singein
Author-email: singein@outlook.com
License: MIT
Platform: UNKNOWN
Requires-Dist: django
